<xml>
<EQUATIONS_OF_STATE>
<EQUATION_TYPE>
Keane
</EQUATION_TYPE>
<CHI_SQUARE>
       2.687527406536E-12
</CHI_SQUARE>
</EQUATIONS_OF_STATE>
<EQUATIONS_PARAMETERS>
<EQUILIBRIUM_VOLUME_AU_A>
    1.044442840542426E+02    1.547704609749455E+01
</EQUILIBRIUM_VOLUME_AU_A>
<BULK_MODULUS_KBAR>
    3.422452451901636E+03
</BULK_MODULUS_KBAR>
<DERIVATIVE_BULK_MODULUS>
    1.099019426235851E+00
</DERIVATIVE_BULK_MODULUS>
<SECOND_DERIVATIVE_BULK_MODULUS>
    2.131633189458565E-04
</SECOND_DERIVATIVE_BULK_MODULUS>
<MINIMUM_ENERGY_RY>
   -4.189478922937995E+00
</MINIMUM_ENERGY_RY>
<CELL_FACTOR>
    2.500000000000000E-01
</CELL_FACTOR>
<CELL_PARAMETER_AU_A>
    7.475637309700437E+00    3.955936901269683E+00
</CELL_PARAMETER_AU_A>
</EQUATIONS_PARAMETERS>
<FIT_CHECK>
<NUMBER_OF_DATA>
      15
</NUMBER_OF_DATA>
<VOL_ENE_EFIT_DELTA_P_GIBBS>
    9.253114510354530E+01   -4.184658000000000E+00   -4.184656863375788E+00   -1.136624211639514E-06    2.881108007501212E+02   -4.003432289881096E+00
    9.419305774570500E+01   -4.186012000000000E+00   -4.186014306618906E+00    2.306618905656421E-06    2.418123005543952E+02   -4.031176828946171E+00
    9.587514735531533E+01   -4.187129000000000E+00   -4.187130178045896E+00    1.178045896388369E-06    1.971942170607403E+02   -4.058608456635146E+00
    9.757714441521698E+01   -4.188020000000000E+00   -4.188015713708472E+00   -4.286291527932917E-06    1.541963912314121E+02   -4.085739074754639E+00
    9.929916603563412E+01   -4.188682000000000E+00   -4.188682268781320E+00    2.687813198676281E-07    1.127510137833626E+02   -4.112572583834034E+00
    1.010409193429835E+02   -4.189139000000000E+00   -4.189140895591289E+00    1.895591289269305E-06    7.280266407577541E+01   -4.139133601242103E+00
    1.028033366614023E+02   -4.189402000000000E+00   -4.189402732347180E+00    7.323471793441172E-07    3.427109490368148E+01   -4.165451889347944E+00
    1.045861298436087E+02   -4.189479000000000E+00   -4.189478371060112E+00   -6.289398886138997E-07   -2.892854347781801E+00   -4.191535709690492E+00
    1.063894159998269E+02   -4.189378000000000E+00   -4.189378340223993E+00    3.402239929783946E-07   -3.874513479083297E+01   -4.217399277754313E+00
    1.082128830783967E+02   -4.189115000000000E+00   -4.189113061645839E+00   -1.938354161623579E-06   -7.333115806809340E+01   -4.243058589955422E+00
    1.100575016500133E+02   -4.188692000000000E+00   -4.188692570177641E+00    5.701776411015658E-07   -1.067180101281925E+02   -4.268533686615585E+00
    1.119229644989137E+02   -4.188125000000000E+00   -4.188126896597707E+00    1.896597706441128E-06   -1.389460304446474E+02   -4.293840260092531E+00
    1.138089449024958E+02   -4.187427000000000E+00   -4.187426040804317E+00   -9.591956828813863E-07   -1.700544336939234E+02   -4.318990885314705E+00
    1.157164426911433E+02   -4.186600000000000E+00   -4.186599333133073E+00   -6.668669270126770E-07   -2.001020418046483E+02   -4.344005146659200E+00
    1.176451360603468E+02   -4.185656000000000E+00   -4.185656427888465E+00    4.278884651043313E-07   -2.291237239618989E+02   -4.368894348792542E+00
</VOL_ENE_EFIT_DELTA_P_GIBBS>
</FIT_CHECK>
